gamengine2d/__init__.py
gamengine2d/engine.py
gamengine2d/helper.py
gamengine2d/objects.py
gamengine2d/shaders.py
gamengine2d/ui_elements.py
gamengine2d-2.21.0.dist-info/licenses/LICENSE.txt
gamengine2d-2.21.0.dist-info/METADATA
gamengine2d-2.21.0.dist-info/WHEEL
gamengine2d-2.21.0.dist-info/top_level.txt
gamengine2d-2.21.0.dist-info/RECORD
