Metadata-Version: 2.4
Name: gamengine2d
Version: 2.21.0
Summary: A Unity-like 2D engine in Python using pygame
Author-email: Samarth Javagal <samarthjavagal@gmail.com>
Classifier: Programming Language :: Python :: 3
Classifier: License :: OSI Approved :: MIT License
Classifier: Topic :: Games/Entertainment
Classifier: Operating System :: OS Independent
Requires-Python: >=3.8
License-File: LICENSE.txt
Requires-Dist: pygame>=2.0.0
Requires-Dist: moderngl>=5.12.0
Requires-Dist: numpy
Dynamic: license-file
